compreq/__init__.py
compreq/bounds.py
compreq/classifiers.py
compreq/contexts.py
compreq/lazy.py
compreq/levels.py
compreq/operators.py
compreq/paths.py
compreq/py.typed
compreq/pypireleases.py
compreq/pythonftp.py
compreq/pythonreleases.py
compreq/releases.py
compreq/requirements.py
compreq/roots.py
compreq/rounding.py
compreq/time.py
compreq/versiontokens.py
compreq/virtualenv.py
compreq/io/__init__.py
compreq/io/poetry.py
compreq/io/pyproject.py
compreq/io/re.py
compreq/io/text.py
compreq/scripts/__init__.py
compreq/scripts/get_distribution_metadata.py
compreq-0.4.0.dist-info/METADATA
compreq-0.4.0.dist-info/WHEEL
compreq-0.4.0.dist-info/licenses/LICENSE
compreq-0.4.0.dist-info/RECORD
