Metadata-Version: 2.4
Name: compreq
Version: 0.4.0
Summary: A library for dynamically computing Python requirements, to keep them up-to-date.
Author-email: Jesper Nielsen <jespernielsen1982+compreq@gmail.com>
License-Expression: MIT
License-File: LICENSE
Classifier: Development Status :: 4 - Beta
Classifier: Intended Audience :: Developers
Classifier: Programming Language :: Python :: 3
Classifier: Programming Language :: Python :: 3.10
Classifier: Programming Language :: Python :: 3.11
Classifier: Programming Language :: Python :: 3.12
Classifier: Programming Language :: Python :: 3.13
Classifier: Typing :: Typed
Requires-Python: <4,>=3.10
Requires-Dist: beautifulsoup4<5,>=4.11.0
Requires-Dist: packaging<26,>=24.1
Requires-Dist: pip<26,>=24.1
Requires-Dist: python-dateutil<3,>=2.7.0
Requires-Dist: requests<3,>=2.30.0
Requires-Dist: tomlkit<0.14,>=0.11.0
Requires-Dist: typing-extensions<5,>=4.12.0
Requires-Dist: virtualenv<21,>=20.26.0
